Saka/__init__.py
Saka/_tricks.py
Saka/cerebro.py
Saka/influxConn.py
Saka/api/__init__.py
Saka/api/data_api.py
Saka/api/influx_api.py
Saka/api/metaNeuron.py
Saka-1.0.2.dist-info/LICENSE
Saka-1.0.2.dist-info/METADATA
Saka-1.0.2.dist-info/WHEEL
Saka-1.0.2.dist-info/top_level.txt
Saka-1.0.2.dist-info/RECORD
